pycsp3_solvers_extra/__init__.py
pycsp3_solvers_extra/loader.py
pycsp3_solvers_extra/solver.py
pycsp3_solvers_extra/backends/__init__.py
pycsp3_solvers_extra/backends/base.py
pycsp3_solvers_extra/backends/cpo_backend.py
pycsp3_solvers_extra/backends/ortools_backend.py
pycsp3_solvers_extra/backends/z3_backend.py
pycsp3_solvers_extra/transforms/__init__.py
pycsp3_solvers_extra/transforms/capabilities.py
pycsp3_solvers_extra/transforms/context.py
pycsp3_solvers_extra/transforms/decompose.py
pycsp3_solvers_extra/transforms/normalize.py
pycsp3_solvers_extra/transforms/pipeline.py
pycsp3_solvers_extra/transforms/rewrite.py
pycsp3_solvers_extra/transforms/types.py
pycsp3_solvers_extra/utils/__init__.py
pycsp3_solvers_extra-0.2.0.dist-info/METADATA
pycsp3_solvers_extra-0.2.0.dist-info/WHEEL
pycsp3_solvers_extra-0.2.0.dist-info/top_level.txt
pycsp3_solvers_extra-0.2.0.dist-info/RECORD
