Metadata-Version: 2.4
Name: pycsp3-solvers-extra
Version: 0.2.0
Summary: Extra solver backends for pycsp3 (OR-Tools, IBM CPO, Z3)
Author: Sohaib AFIFI
License: MIT
Project-URL: Homepage, https://github.com/sohaibafifi/pycsp3-solvers-extra
Project-URL: Documentation, https://github.com/sohaibafifi/pycsp3-solvers-extra
Project-URL: Repository, https://github.com/sohaibafifi/pycsp3-solvers-extra
Keywords: constraint-programming,csp,xcsp3,pycsp3,or-tools,cplex,z3,optimization
Classifier: Development Status :: 3 - Alpha
Classifier: Intended Audience :: Developers
Classifier: Intended Audience :: Science/Research
Classifier: License :: OSI Approved :: MIT License
Classifier: Programming Language :: Python :: 3
Classifier: Programming Language :: Python :: 3.10
Classifier: Programming Language :: Python :: 3.11
Classifier: Programming Language :: Python :: 3.12
Classifier: Topic :: Scientific/Engineering :: Artificial Intelligence
Classifier: Topic :: Scientific/Engineering :: Mathematics
Requires-Python: <=3.12,>=3.10
Requires-Dist: pycsp3>=2.2
Provides-Extra: ortools
Requires-Dist: ortools>=9.0; extra == "ortools"
Provides-Extra: cpo
Requires-Dist: docplex>=2.25; extra == "cpo"
Provides-Extra: z3
Requires-Dist: z3-solver>=4.8; extra == "z3"
Provides-Extra: all
Requires-Dist: ortools>=9.0; extra == "all"
Requires-Dist: docplex>=2.25; extra == "all"
Requires-Dist: z3-solver>=4.8; extra == "all"
Provides-Extra: dev
Requires-Dist: pytest>=7.0; extra == "dev"
Requires-Dist: pytest-cov>=4.0; extra == "dev"
